bball_reports/__init__.py
bball_reports-0.1.2.dist-info/METADATA
bball_reports-0.1.2.dist-info/WHEEL
bball_reports-0.1.2.dist-info/RECORD
